nocton/__init__.py
nocton/apps.py
nocton/account_validation/__init__.py
nocton/account_validation/admin.py
nocton/account_validation/apps.py
nocton/account_validation/backends.py
nocton/account_validation/generic_backend.py
nocton/account_validation/models.py
nocton/account_validation/tools.py
nocton/account_validation/views.py
nocton/account_validation/migrations/0001_initial.py
nocton/account_validation/migrations/0002_auto_20200514_1017.py
nocton/account_validation/migrations/__init__.py
nocton/generics/__init__.py
nocton/generics/exceptions.py
nocton/generics/model_validators.py
nocton/generics/permissions.py
nocton/generics/send_email.py
nocton/generics/views/__init__.py
nocton/generics/views/core_views.py
nocton/migrations/__init__.py
nocton/setup/__init__.py
nocton/setup/settings.py
nocton/tools/__init__.py
nocton/tools/console.py
nocton/tools/model_manip.py
nocton/tools/serializers_manip.py
nocton/watch/__init__.py
nocton-0.1.dist-info/LICENSE
nocton-0.1.dist-info/METADATA
nocton-0.1.dist-info/WHEEL
nocton-0.1.dist-info/top_level.txt
nocton-0.1.dist-info/RECORD
