Metadata-Version: 2.1
Name: nocton
Version: 0.1
Summary: Um app simples para API's que utiliza django-rest-framework
Home-page: https://github.com/PauloE314/nocton
Author: Paulo Eduardo de Lima Lourenço
Author-email: pauloeduardodelima155@gmail.com
License: UNKNOWN
Platform: UNKNOWN
Classifier: Environment :: Web Environment
Classifier: Framework :: Django
Classifier: Operating System :: OS Independent
Classifier: Programming Language :: Python :: 3
Classifier: License :: OSI Approved :: MIT License
Classifier: Topic :: Internet :: WWW/HTTP
Requires-Python: >=3.0
Requires-Dist: django
Requires-Dist: djangorestframework
Requires-Dist: psycopg2
Requires-Dist: django-cors-headers
